semantic_memory/__init__.py
semantic_memory/list_utils.py
semantic_memory/memory.py
semantic_memory/taxonomy.py
semantic_memory/vsm.py
semantic_memory/vsm_utils.py
semantic_memory-0.1.15.dist-info/LICENSE
semantic_memory-0.1.15.dist-info/METADATA
semantic_memory-0.1.15.dist-info/WHEEL
semantic_memory-0.1.15.dist-info/RECORD
